relgen/__init__.py
relgen/data/__init__.py
relgen/data/column.py
relgen/data/data_processor.py
relgen/data/data_transformer.py
relgen/data/dataset.py
relgen/data/metadata.py
relgen/data/table.py
relgen/data/test_metadata.py
relgen/data/utils.py
relgen/evaluator/__init__.py
relgen/evaluator/evaluator.py
relgen/model/__init__.py
relgen/model/base_model.py
relgen/model/armodel/__init__.py
relgen/model/armodel/ar_model.py
relgen/model/armodel/made.py
relgen/model/armodel/modules.py
relgen/model/diffusionmodel/__init__.py
relgen/model/diffusionmodel/diffusion_model.py
relgen/model/diffusionmodel/modules.py
relgen/model/diffusionmodel/relddpm.py
relgen/model/diffusionmodel/utils.py
relgen/synthesizer/__init__.py
relgen/synthesizer/base_synthesizer.py
relgen/synthesizer/arsynthesizer/__init__.py
relgen/synthesizer/arsynthesizer/ar_synthesizer.py
relgen/synthesizer/arsynthesizer/made_synthesizer.py
relgen/synthesizer/arsynthesizer/test_made_synthesizer.py
relgen/synthesizer/diffusionsynthesizer/__init__.py
relgen/synthesizer/diffusionsynthesizer/diffusion_synthesizer.py
relgen/synthesizer/diffusionsynthesizer/relddpm_synthesizer.py
relgen/synthesizer/diffusionsynthesizer/resample.py
relgen/synthesizer/diffusionsynthesizer/test_relddpm_synthesizer.py
relgen/utils/__init__.py
relgen/utils/constant.py
relgen/utils/enum_type.py
relgen-0.1.1.dist-info/LICENSE
relgen-0.1.1.dist-info/METADATA
relgen-0.1.1.dist-info/WHEEL
relgen-0.1.1.dist-info/top_level.txt
relgen-0.1.1.dist-info/RECORD
