Metadata-Version: 2.1
Name: relgen
Version: 0.1.1
Summary: A tool for relational data generation
Home-page: https://github.com/ruc-datalab/RelGen
Author: ruc-datalab
Author-email: ltyzzz@ruc.edu.cn
License: Apache-2.0
Classifier: Programming Language :: Python :: 3
Classifier: License :: OSI Approved :: Apache Software License
Classifier: Operating System :: OS Independent
Requires-Python: >=3.7
License-File: LICENSE
Requires-Dist: pandas
Requires-Dist: numpy
Requires-Dist: scipy
Requires-Dist: torch
Requires-Dist: scikit-learn
Requires-Dist: matplotlib
Requires-Dist: dython
Requires-Dist: tqdm
Requires-Dist: pytest
